[{"_path":"/dir/georgia_motorcycle_safety_program","_dir":"dir","_draft":false,"_partial":false,"_locale":"","title":"Georgia Motorcycle Safety Program","description":"Enhance your motorcycle skills with certified training and exclusive license test waivers.","featured":false,"invert":false,"card_image":"ddslogo.png","tags":["Professional Rider Coaches","DMV Test Waiver","Motorcycle Licensing","Rider Safety Gear","Motorcycle Endorsement","Basic Rider Training","Motorcycle Safety Courses"],"_type":"markdown","_id":"content:dir:Georgia_Motorcycle_Safety_Program.md","_source":"content","_file":"dir/Georgia_Motorcycle_Safety_Program.md","_stem":"dir/Georgia_Motorcycle_Safety_Program","_extension":"md","sitemap":{"loc":"/dir/georgia_motorcycle_safety_program"}},{"_path":"/dir/iowa_motor_vehicle_division","_dir":"dir","_draft":false,"_partial":false,"_locale":"","title":"Iowa Motor Vehicle Division","description":"Enhance your riding skills with Iowa's comprehensive courses, from beginners to advanced, focusing on safety and hazard awareness.","featured":false,"invert":false,"card_image":"logo_footer_1.png","tags":["Professional Rider Coaches","Motorcycle Safety Certification","Motorcycle Safety Foundation","Training Locations Map","DMV Test Waiver","Motorcycle Licensing","Three-Wheel Motorcycle Training","Motorcycle Endorsement","Advanced Riding Skills","Basic Rider Training","Motorcycle Safety Courses"],"_type":"markdown","_id":"content:dir:Iowa_Motor_Vehicle_Division.md","_source":"content","_file":"dir/Iowa_Motor_Vehicle_Division.md","_stem":"dir/Iowa_Motor_Vehicle_Division","_extension":"md","sitemap":{"loc":"/dir/iowa_motor_vehicle_division"}}]