[{"_path":"/blog/top-5-tailored-motorcycle-training-programs-enhance-riding-skills","_dir":"blog","_draft":false,"_partial":false,"_locale":"","title":"Top 5 Tailored Motorcycle Training Programs to Enhance Your Riding Skills","description":"Motorcycle enthusiasts at every level know that honing one’s skills is crucial for both safety and enjoyment on the road. Whether you're a beginner or an experienced rider, tailored motorcycle training programs offer exceptional opportunities to refine your abilities and tackle specific challenges on the asphalt or dirt. Here, we explore five standout programs that provide personalized motorcycle training to enhance your riding skills.","_type":"markdown","_id":"content:blog:top-5-tailored-motorcycle-training-programs-enhance-riding-skills.md","_source":"content","_file":"blog/top-5-tailored-motorcycle-training-programs-enhance-riding-skills.md","_stem":"blog/top-5-tailored-motorcycle-training-programs-enhance-riding-skills","_extension":"md","sitemap":{"loc":"/blog/top-5-tailored-motorcycle-training-programs-enhance-riding-skills"}},{"_path":"/blog/understanding_motorcycle_dmv_test_waivers_by_state","_dir":"blog","_draft":false,"_partial":false,"_locale":"","title":"Understanding Motorcycle DMV Test Waivers by State","description":"Navigating the process of obtaining a motorcycle license can be complex, especially with different requirements across various states. However, many states offer DMV test waivers upon completing approved safety courses, simplifying the procedure significantly. These waivers generally allow riders to bypass the skills test by validating their proficiency through a course. Here's a comprehensive overview of DMV test waivers offered in several states and by top motorcycle safety organizations.","_type":"markdown","_id":"content:blog:understanding_motorcycle_dmv_test_waivers_by_state.md","_source":"content","_file":"blog/understanding_motorcycle_dmv_test_waivers_by_state.md","_stem":"blog/understanding_motorcycle_dmv_test_waivers_by_state","_extension":"md","sitemap":{"loc":"/blog/understanding_motorcycle_dmv_test_waivers_by_state"}}]